{
    "lectureCode": "B10102",
    "courseName": "微分積分[2]BS",
    "lecturer": [
        "松永栄一(兼任講師)"
    ],
    "regularOrIntensive": "専門基礎教育科目",
    "courseType": "講義科目",
    "courseStart": "2024年度後期",
    "classPeriod": [
        "火2"
    ],
    "targetDepartment": "応用生物学部応用生物学科",
    "targetGrade": [
        "1年",
        "2年",
        "3年",
        "4年"
    ],
    "numberOfCredits": 2,
    "classroom": [
        "講義棟Ａ２０４"
    ],
    "courceDetails": {
        "courseOverview": "「微分積分学」は自然科学・工学・社会科学などの分野に幅広く応用されている極めて重要な基礎科目である．「微分積分」では微分法および積分法の基礎について習得する．具体的には，関数と極限，様々な関数の微分法，そして積分法に関する講義，および演習を行う．",
        "outcomesMeasuredBy": "本講義では，微分法および積分法の演習を中心に行うことで基礎的な数学力の向上を図り，それに付随する「論理的な思考力」，「問題解決力」および，「分析・評価能力」を身に付ける．",
        "learningOutcomes": "論理的な思考力分析・評価能力問題解決力",
        "teachingMethod": "まず，授業計画に応じた内容に関する講義を行う．次に，演習問題を用いて反復練習することで講義内容や解法を習得する．そしてさらに解説を行い，内容に対する理解を深める．ノートPCは使用しない．",
        "notices": "三角関数，指数関数，および対数関数の基本的な法則を理解して授業に臨むこと．",
        "preparatoryStudy": "授業の前に，教科書の該当する部分を精読し，わからない部分を明らかにして授業に臨むこと．また，授業後は教科書，および講義中に出題された問題を再度解答し，解法の習得に努めること．",
        "gradingGuidelines": "授業への出席を前提として，期末試験を70%，授業中に出題する提出課題を30%で評価し，100点満点中60点以上で単位認定とする．また，提出課題の解答状況を元に，講義の中で学修状況に関するフィードバックを適宜行う予定である．",
        "textbook": "理工系入門微分積分石原繁浅野重初共著裳華房",
        "referenceMaterials": "適宜，授業内で指示する．",
        "courseSchedule": "第1回：数列と級数第2回：関数と極限第3回：関数の連続性第4回：導関数の定義と計算第5回：関数の微分法第6回：指数関数の微分法第7回：対数関数の微分法第8回：三角関数の微分法第9回：合成関数の微分法第10回：微分法のまとめ第11回：積分法の基礎第12回：不定積分と定積分第13回：置換積分法と部分積分法第14回：積分法のまとめ",
        "courseDataUpdatedAt": "2024\/01\/31"
    },
    "updateAt": "2024\/09\/13"
}