{
    "lectureCode": "W2307",
    "courseName": "生体機能代行装置学演習",
    "lecturer": [
        "笠井亮佑(医療保健学部臨床工学科)",
        "島峰徹也(医療保健学部臨床工学科)",
        "安藤ゆうき(医療保健学部臨床工学科)",
        "佐藤広隆(医療保健学部臨床工学科)"
    ],
    "regularOrIntensive": "専門科目",
    "courseType": "演習科目",
    "courseStart": "2024年度前期",
    "classPeriod": [
        "月4"
    ],
    "targetDepartment": "医療保健学部",
    "targetGrade": [
        "3年",
        "4年"
    ],
    "numberOfCredits": "1",
    "classroom": [
        "３１０１２教室"
    ],
    "courceDetails": {
        "courseOverview": "臨床工学技士の業務の中で主に取り扱う体外循環装置、呼吸療法装置、血液浄化装置について、理論をもとにより実践的な操作技能・技術を学ぶ。この科目は、実務経験を有する専門職が、その経験に基づいた講義を行う実践的科目である。",
        "outcomesMeasuredBy": "(1)装置の基本原理等を理解し、基本的な操作技能・技術を理解する。(2)各種機器を適正に保守管理することができる。",
        "learningOutcomes": "実学に基づく専門能力コミュニケーション能力論理的な思考力分析・評価能力問題解決力",
        "teachingMethod": "グループ別に講義を行い、その後実際の装置を扱いながら演習を行う。ディスカッション等の学生自らの主体的学び（アクティブラーニング）を行う。",
        "notices": "(1)１回目のオリエンテーションにて説明する。指示された実習着で演習を行う。取り扱い法を誤ると危険な装置もあるため指導教員の指示に従って演習を行うこと。(2)生体機能代行装置学実習と連動して行われることがある。",
        "preparatoryStudy": "事前に実習指導書を読み、実習内容を把握しておくこと。生体機能代行装置学実習の復習と共に体外循環学演習、呼吸療法学演習、血液浄化学演習の復習をする。また適応を理解するためには、内科系・外科系臨床医学で学ぶ関連疾患について、その治療法を把握しておくことが望ましい。",
        "gradingGuidelines": "実習到達度（口頭試問及び確認テスト、レポートなどから総合的に評価（100%）また、評価法にはルーブリックを用いて行う。",
        "textbook": "演習指導書を配布する。",
        "referenceMaterials": "(1)「ＭＥの基礎知識と安全管理改訂第8版」南江堂(2)「臨床工学技士標準テキスト第4版」金原出版",
        "courseSchedule": "第１回：生体機能代行装置学実習に関するガイダンス・オリエンテーション①：循環管理（全教員）第２回：生体機能代行装置学実習に関するガイダンス・オリエンテーション②：呼吸管理（全教員）第３回：生体機能代行装置学実習に関するガイダンス・オリエンテーション③：代謝管理（全教員）第４回：循環管理：ECMO・IABP・人工心肺装置に関する演習（全教員）第５回：循環管理：心臓カテーテルに関する演習（全教員）第６回：呼吸管理：呼吸管理・気道管理に関する演習（全教員）第７回：呼吸管理：酸素療法・NPPVに関する演習（全教員）第８回：代謝管理：装置操作装置操作に関する演習（全教員）第９回：代謝管理：ふるい係数・保守管理に関する演習（全教員）第１０回：循環管理に関する講義（外部講師）第１１回：循環管理に関する演習（外部講師）第１２回：呼吸管理に関する講義（外部講師）第１３回：呼吸管理に関する演習（外部講師）第１４回：代謝管理に関する講義（外部講師）第１５回：代謝管理に関する演習（外部講師）",
        "courseDataUpdatedAt": "2023\/12\/28"
    },
    "updateAt": "2024\/09\/12"
}