{
    "lectureCode": "U63209",
    "courseName": "聴覚心理学",
    "lecturer": [
        "米本清(兼任講師)"
    ],
    "regularOrIntensive": "専門基礎科目",
    "courseType": "講義科目",
    "courseStart": "2024年度後期",
    "classPeriod": [
        "水3",
        "水4"
    ],
    "targetDepartment": "医療保健学部",
    "targetGrade": [
        "2年",
        "3年",
        "4年"
    ],
    "numberOfCredits": 1,
    "classroom": [
        "３０２０２教室"
    ],
    "courceDetails": {
        "courseOverview": "「聴覚心理学」は一般的にイメージされている心理学とは異なり、繊細な実験を繰り返した結果を基に「聞こえ」や「聞取り」の基礎となる知見を得ようとする分野です。多くは厳密さを要求されるものですので、音響学はもちろんのこと一定レベルの数学的センスも要求されます。ただ、自分自身の普段の生活にも直結した内容ですので、日常生活場面に存在する様々な環境音に対してより深く興味を持つことができ楽しめることと思います。",
        "outcomesMeasuredBy": "聴覚に関わる臨床現場での応用力を養うことを目標とし、聴覚のさまざまな現象を将来の臨床における問題解決力と関連付けて論理的に考え、分析・評価できるような能力を身につけるようにすること。",
        "learningOutcomes": "実学に基づく専門能力論理的な思考力分析・評価能力",
        "teachingMethod": "パワーポイントにより各項目の解説を行いながら、実際の音を聞いて経験することで自らその内容を理解できるようにする。",
        "notices": "音響学の講義内容を十分に理解していること。特に指数や対数に関わる最低限の基礎的知識を備えていること。",
        "preparatoryStudy": "前回までの講義内容を十分に理解しておくこと。（授業時に実施する小テストで確認）",
        "gradingGuidelines": "授業内で数回のミニテスト（100点満点）と期末の筆記試験（100点満点）で合計得点が60％以上であること。",
        "textbook": "吉田友敬著，言語聴覚士の音響学入門2訂版，海文堂出版（2020）（音響学のテキストと共通）必要に応じて講義資料を配布する。",
        "referenceMaterials": "聴覚と音響心理（音響学会編：コロナ社）音響聴覚心理学（大串健吾著：誠信書房）",
        "courseSchedule": "第1-2回音響学の復習（pp1-104）第3-4回音の大きさの知覚１(pp105-118)第5-6回音の大きさの知覚２(pp105-118)第7-8回音の高さの知覚１(pp119-129)第9-10回音の高さの知覚２(pp119-129)第11-12回マスキング（pp130-135）第13-14回両耳聴(pp136-146)第15回聴覚心理学領域の国試問題(pp203-208)カッコ内はテキストの該当ページ",
        "courseDataUpdatedAt": "2024/03/06"
    },
    "updateAt": "2024/12/09"
}